xloop/__init__.py
xloop-1.1.0.dist-info/LICENSE
xloop-1.1.0.dist-info/METADATA
xloop-1.1.0.dist-info/WHEEL
xloop-1.1.0.dist-info/RECORD
