Metadata-Version: 2.1
Name: xloop
Version: 1.1.0
Summary: General purpose for/iterator looping generators/utilities.
Home-page: https://github.com/xyngular/py-xloop
Keywords: forloop,loop,list,generator,utilites
Author: Josh Orr
Author-email: josh@orr.blue
Requires-Python: >=3.11,<4.0
Classifier: License :: OSI Approved :: The Unlicense (Unlicense)
Classifier: Programming Language :: Python :: 3
Classifier: Programming Language :: Python :: 3.11
Classifier: Programming Language :: Python :: 3.12
Classifier: Topic :: Software Development :: Libraries :: Python Modules
Requires-Dist: xsentinels (>=1.2.2,<2.0.0)
Project-URL: Repository, https://github.com/xyngular/py-xloop
